leibnetz/__init__.py
leibnetz/leibnet.py
leibnetz/local_learning.py
leibnetz/model_wrapper.py
leibnetz/nets/__init__.py
leibnetz/nets/attentive_scalenet.py
leibnetz/nets/scalenet.py
leibnetz/nets/unet.py
leibnetz/nodes/__init__.py
leibnetz/nodes/additive_attention_gate_node.py
leibnetz/nodes/conv_pass_node.py
leibnetz/nodes/conv_resample_node.py
leibnetz/nodes/node.py
leibnetz/nodes/node_ops.py
leibnetz/nodes/resample_node.py
leibnetz/nodes/resample_ops.py
leibnetz/nodes/wrapper_node.py
leibnetz-2025.11.13.1849.dist-info/METADATA
leibnetz-2025.11.13.1849.dist-info/WHEEL
leibnetz-2025.11.13.1849.dist-info/licenses/LICENSE
leibnetz-2025.11.13.1849.dist-info/RECORD
