Metadata-Version: 2.4
Name: leibnetz
Version: 2025.11.13.1849
Summary: A lightweight and modular library for rapidly developing and constructing PyTorch models for deep learning.
Project-URL: Homepage, https://github.com/janelia-cellmap/LeibNetz
Project-URL: Repository, https://github.com/janelia-cellmap/LeibNetz
Project-URL: Documentation, https://github.com/janelia-cellmap/LeibNetz
Project-URL: Issues, https://github.com/janelia-cellmap/LeibNetz/issues
Author-email: Jeff Rhoades <rhoadesj@alumni.harvard.edu>
Maintainer-email: Jeff Rhoades <rhoadesj@alumni.harvard.edu>
License: BSD 3-Clause License
License-File: LICENSE
Keywords: deep learning,machine learning,neural networks,pytorch
Classifier: Development Status :: 4 - Beta
Classifier: Intended Audience :: Developers
Classifier: Intended Audience :: Science/Research
Classifier: License :: OSI Approved :: BSD License
Classifier: Operating System :: OS Independent
Classifier: Programming Language :: Python :: 3
Classifier: Programming Language :: Python :: 3.10
Classifier: Programming Language :: Python :: 3.11
Classifier: Programming Language :: Python :: 3.12
Classifier: Topic :: Scientific/Engineering :: Artificial Intelligence
Classifier: Topic :: Software Development :: Libraries :: Python Modules
Requires-Python: >=3.10
Requires-Dist: networkx
Requires-Dist: numpy
Requires-Dist: torch
Requires-Dist: torchvision
Provides-Extra: dev
Requires-Dist: black>=22.0; extra == 'dev'
Requires-Dist: flake8>=4.0; extra == 'dev'
Requires-Dist: isort>=5.0; extra == 'dev'
Requires-Dist: mypy>=0.900; extra == 'dev'
Requires-Dist: pre-commit>=2.0; extra == 'dev'
Requires-Dist: pytest-cov>=2.0; extra == 'dev'
Requires-Dist: pytest-xdist>=2.0; extra == 'dev'
Requires-Dist: pytest>=6.0; extra == 'dev'
Provides-Extra: docs
Requires-Dist: myst-parser>=0.15; extra == 'docs'
Requires-Dist: sphinx-rtd-theme>=1.0; extra == 'docs'
Requires-Dist: sphinx>=4.0; extra == 'docs'
Provides-Extra: lint
Requires-Dist: black>=22.0; extra == 'lint'
Requires-Dist: flake8>=4.0; extra == 'lint'
Requires-Dist: isort>=5.0; extra == 'lint'
Requires-Dist: mypy>=0.900; extra == 'lint'
Provides-Extra: test
Requires-Dist: pytest-cov>=2.0; extra == 'test'
Requires-Dist: pytest-xdist>=2.0; extra == 'test'
Requires-Dist: pytest>=6.0; extra == 'test'
